setup.py
stats_distributions_package/Binomialdistribution.py
stats_distributions_package/Gaussiandistribution.py
stats_distributions_package/Generaldistribution.py
stats_distributions_package/__init__.py
stats_distributions_package.egg-info/PKG-INFO
stats_distributions_package.egg-info/SOURCES.txt
stats_distributions_package.egg-info/dependency_links.txt
stats_distributions_package.egg-info/not-zip-safe
stats_distributions_package.egg-info/top_level.txt